cmdplug/__init__.py
cmdplug/command.py
cmdplug/registry.py
cmdplug-1.0.0.dist-info/METADATA
cmdplug-1.0.0.dist-info/WHEEL
cmdplug-1.0.0.dist-info/top_level.txt
cmdplug-1.0.0.dist-info/RECORD
