Metadata-Version: 2.4
Name: cmdplug
Version: 1.0.0
Summary: Create simple commands in Python with ease!
Author: HeapX
Author-email: HeapX <dltmddyd645@naver.com>
License: MIT
Project-URL: Repository, https://github.com/Security-Development/cmdplug
Classifier: Programming Language :: Python :: 3
Classifier: Programming Language :: Python :: 3 :: Only
Classifier: License :: OSI Approved :: MIT License
Classifier: Operating System :: OS Independent
Dynamic: author
